{
	"Functions":{
		"type":"select",
		"category":"功能",
		"options": [
					["Congestion","车道拥堵监测"],
					["Illegal_parking","违章停车监测"],
					["Retrograde_motion","逆行检测"],
					["Obstacle","障碍物检测"],
					["Pedestrian","行人检测"]
				],
		"values": [],
		"checkbox":"TRUE",
        "ui_name": "功能"
	},
    "Area": {
        "category": "",
        "color": {
            "b": 255,
            "g": 0,
            "r": 0
        },
		"color1": {
            "b": 0,
            "g": 0,
            "r": 255
        },
		"labels": [
		],
		"labelDict":[
			{
				"name": "cross_type",
				"ui_name": "车道类别",
				"options": [
					["0","普通路口"],
					["1","交通路口"]
				],
				"default":"0"
			},
			{
				"name": "direction",
				"ui_name": "车道类别",
				"options": [
					["0","正向"],
					["1","反向"]
				],
				"default":"0"
			}
			
		],
        "polygons": [
        ],
        "type": "polygons",
        "ui_name": "区域"
    },
	"Masks": {
        "category": "",
        "color": {
            "b": 255,
            "g": 0,
            "r": 0
        },
		"color1": {
            "b": 0,
            "g": 255,
            "r": 255
        },
		
        "polygons": [
        ],
		"labels": [
		],
		"bindings":[
		],
		"labelDict":[
			{
				"name": "roadway",
				"ui_name": "车道类别",
				"options": [
					["L","左转道"],
					["R","右转道"],
					["S","直行道"],
					["LS","直行&左转道"],
					["RS","直行&右转道"]
				],
				"default":"L"
			}
			
		],
		"bingTargets":[
			"Area"
		],
		"type": "polygons",
		"ui_name": "车道"
	}
}
